LMMH/__init__.py
LMMH/app.py
lmmh-0.1.1.dist-info/licenses/LICENSE
lmmh-0.1.1.dist-info/METADATA
lmmh-0.1.1.dist-info/WHEEL
lmmh-0.1.1.dist-info/entry_points.txt
lmmh-0.1.1.dist-info/top_level.txt
lmmh-0.1.1.dist-info/RECORD
