Metadata-Version: 2.4
Name: LMMH
Version: 0.1.1
Summary: 👽 LMMH - Comprehensive Library of AI
Home-page: https://github.com/LaithALhaware
Author: Laith Madhat M. AL-Haware
Author-email: www.landr41@gmail.com
Classifier: Programming Language :: Python :: 3
Classifier: License :: OSI Approved :: MIT License
Classifier: Operating System :: OS Independent
Requires-Python: >=3.8
License-File: LICENSE
Dynamic: author
Dynamic: author-email
Dynamic: classifier
Dynamic: description
Dynamic: description-content-type
Dynamic: home-page
Dynamic: license-file
Dynamic: requires-python
Dynamic: summary
